medcat/__init__.py
medcat/__main__.py
medcat/cat.py
medcat/py.typed
medcat/trainer.py
medcat/version.py
medcat/vocab.py
medcat/cdb/__init__.py
medcat/cdb/cdb.py
medcat/cdb/concepts.py
medcat/components/__init__.py
medcat/components/types.py
medcat/components/addons/__init__.py
medcat/components/addons/addons.py
medcat/components/addons/meta_cat/__init__.py
medcat/components/addons/meta_cat/data_utils.py
medcat/components/addons/meta_cat/meta_cat.py
medcat/components/addons/meta_cat/ml_utils.py
medcat/components/addons/meta_cat/models.py
medcat/components/addons/meta_cat/mctokenizers/__init__.py
medcat/components/addons/meta_cat/mctokenizers/bert_tokenizer.py
medcat/components/addons/meta_cat/mctokenizers/bpe_tokenizer.py
medcat/components/addons/meta_cat/mctokenizers/tokenizers.py
medcat/components/addons/relation_extraction/__init__.py
medcat/components/addons/relation_extraction/base_component.py
medcat/components/addons/relation_extraction/config.py
medcat/components/addons/relation_extraction/ml_utils.py
medcat/components/addons/relation_extraction/models.py
medcat/components/addons/relation_extraction/pad_seq.py
medcat/components/addons/relation_extraction/rel_cat.py
medcat/components/addons/relation_extraction/rel_dataset.py
medcat/components/addons/relation_extraction/tokenizer.py
medcat/components/addons/relation_extraction/bert/__init__.py
medcat/components/addons/relation_extraction/bert/config.py
medcat/components/addons/relation_extraction/bert/model.py
medcat/components/addons/relation_extraction/bert/tokenizer.py
medcat/components/addons/relation_extraction/llama/__init__.py
medcat/components/addons/relation_extraction/llama/config.py
medcat/components/addons/relation_extraction/llama/model.py
medcat/components/addons/relation_extraction/llama/tokenizer.py
medcat/components/addons/relation_extraction/modernbert/__init__.py
medcat/components/addons/relation_extraction/modernbert/config.py
medcat/components/addons/relation_extraction/modernbert/model.py
medcat-2.5.3.dist-info/METADATA
medcat-2.5.3.dist-info/WHEEL
medcat-2.5.3.dist-info/top_level.txt
medcat-2.5.3.dist-info/RECORD
