Metadata-Version: 2.4
Name: medcat
Version: 2.5.3
Summary: Medical Concept Annotation Toolkit (v2)
Author: Z. Kraljevic, A. Shek, T. Searle, X. Bai, M. Ratas
Maintainer-email: CogStack <contact@cogstack.org>
License-Expression: Apache-2.0
Project-URL: Homepage, https://cogstack.org/
Project-URL: Documentation, https://docs.cogstack.org/projects/nlp/en/latest/
Project-URL: Bug Reports, https://discourse.cogstack.org/
Project-URL: Source, https://github.com/CogStack/cogstack-nlp/
Keywords: ML,NLP,NER+L
Classifier: Development Status :: 5 - Production/Stable
Classifier: Intended Audience :: Healthcare Industry
Classifier: Programming Language :: Python :: 3
Classifier: Programming Language :: Python :: 3.10
Classifier: Programming Language :: Python :: 3.11
Classifier: Programming Language :: Python :: 3.12
Classifier: Programming Language :: Python :: 3.13
Classifier: Programming Language :: Python :: 3 :: Only
Classifier: Operating System :: OS Independent
Requires-Python: >=3.10
Requires-Dist: numpy>=2.1; python_version >= "3.13"
Requires-Dist: numpy>=2.0; python_version < "3.13"
Requires-Dist: dill
Requires-Dist: pandas<3.0,>=2.2
Requires-Dist: tqdm<5.0,>=4.64
Requires-Dist: xxhash<4.0,>=3.5.0
Requires-Dist: pydantic>2.0
Requires-Dist: typing-extensions
Requires-Dist: packaging
Requires-Dist: pyyaml
Requires-Dist: requests
Provides-Extra: dev
Requires-Dist: ruff~=0.1.7; extra == "dev"
Requires-Dist: mypy; extra == "dev"
Requires-Dist: types-tqdm; extra == "dev"
Requires-Dist: types-setuptools; extra == "dev"
Requires-Dist: types-PyYAML; extra == "dev"
Provides-Extra: spacy
Requires-Dist: spacy; extra == "spacy"
Provides-Extra: meta-cat
Requires-Dist: transformers<5.0,>=4.41.0; extra == "meta-cat"
Requires-Dist: peft<1.0,>0.8.2; extra == "meta-cat"
Requires-Dist: torch<3.0,>=2.4.0; extra == "meta-cat"
Requires-Dist: scikit-learn<2.0,>=1.1.3; extra == "meta-cat"
Requires-Dist: scipy<1.14; python_version < "3.13" and extra == "meta-cat"
Requires-Dist: scipy>=1.14; python_version >= "3.13" and extra == "meta-cat"
Provides-Extra: dict-ner
Requires-Dist: pyahocorasick<3.0,>=2.1.0; extra == "dict-ner"
Provides-Extra: deid
Requires-Dist: datasets<3.0.0,>=2.2.2; extra == "deid"
Requires-Dist: transformers<5.0,>=4.41.0; extra == "deid"
Requires-Dist: scikit-learn<2.0,>=1.1.3; extra == "deid"
Requires-Dist: torch<3.0,>=2.4.0; extra == "deid"
Requires-Dist: scipy<1.14; python_version < "3.13" and extra == "deid"
Requires-Dist: scipy>=1.14; python_version >= "3.13" and extra == "deid"
Provides-Extra: rel-cat
Requires-Dist: transformers<5.0,>=4.41.0; extra == "rel-cat"
Requires-Dist: scikit-learn<2.0,>=1.1.3; extra == "rel-cat"
Requires-Dist: torch<3.0,>=2.4.0; extra == "rel-cat"
Provides-Extra: embed-linker
Requires-Dist: transformers<5.0,>=4.41.0; extra == "embed-linker"
Requires-Dist: torch<3.0,>=2.4.0; extra == "embed-linker"
Provides-Extra: test
